cnpj_cpf_validator/__init__.py
cnpj_cpf_validator/cnpj.py
cnpj_cpf_validator/cpf.py
cnpj_cpf_validator-0.1.2.dist-info/licenses/LICENSE
cnpj_cpf_validator-0.1.2.dist-info/METADATA
cnpj_cpf_validator-0.1.2.dist-info/WHEEL
cnpj_cpf_validator-0.1.2.dist-info/top_level.txt
cnpj_cpf_validator-0.1.2.dist-info/RECORD
