Metadata-Version: 2.4
Name: cnpj_cpf_validator
Version: 0.1.2
Summary: Biblioteca para validação de CPF e CNPJ brasileiros, incluindo suporte ao novo padrão alfanumérico
Author-email: Frederico Ferreira <frederico.dida1@gmail.com>
License: MIT
Project-URL: Homepage, https://github.com/FredericoSFerreira/py_cnpj_cpf_validator
Project-URL: Bug Tracker, https://github.com/FredericoSFerreira/py_cnpj_cpf_validator
Keywords: cpf,cnpj,validação,brasil,documentos,cnpj alfanumeric,cnpj com letras,validation,validator,govbr,receita federal
Classifier: Programming Language :: Python :: 3
Classifier: Programming Language :: Python :: 3.8
Classifier: Programming Language :: Python :: 3.9
Classifier: Programming Language :: Python :: 3.10
Classifier: Programming Language :: Python :: 3.11
Classifier: Programming Language :: Python :: 3.12
Classifier: Programming Language :: Python :: 3.13
Classifier: License :: OSI Approved :: MIT License
Classifier: Operating System :: OS Independent
Classifier: Development Status :: 4 - Beta
Classifier: Intended Audience :: Developers
Classifier: Topic :: Software Development :: Libraries :: Python Modules
Classifier: Topic :: Office/Business :: Financial
Classifier: Natural Language :: Portuguese (Brazilian)
License-File: LICENSE
Dynamic: license-file
